curvv/__init__.py
curvv/main.py
curvv/_func/__init__.py
curvv/_func/clearCache.py
curvv/_func/end.py
curvv/_func/importModuleLibrary.py
curvv/_func/initialize.py
curvv/_func/packageSafety.py
curvv/_func/wait.py
curvv/_library/__init__.py
curvv/_library/curvv.py
curvv/_library/tsVp.py
curvv-0.4.25.dist-info/LICENSE.txt
curvv-0.4.25.dist-info/METADATA
curvv-0.4.25.dist-info/WHEEL
curvv-0.4.25.dist-info/entry_points.txt
curvv-0.4.25.dist-info/top_level.txt
curvv-0.4.25.dist-info/RECORD
